iptocc/__init__.py
iptocc/delegated-afrinic-extended-latest
iptocc/delegated-apnic-extended-latest
iptocc/delegated-arin-extended-latest
iptocc/delegated-lacnic-extended-latest
iptocc/delegated-ripencc-extended-latest
iptocc/exceptions.py
iptocc/iso3166.csv
iptocc-2.1.2.dist-info/entry_points.txt
iptocc-2.1.2.dist-info/LICENSE
iptocc-2.1.2.dist-info/WHEEL
iptocc-2.1.2.dist-info/METADATA
iptocc-2.1.2.dist-info/RECORD
