Metadata-Version: 2.1
Name: iptocc
Version: 2.1.2
Summary: Get country code of IPv4/IPv6 address. Address lookup is done offline.
Home-page: https://github.com/roniemartinez/IPToCC
License: MIT
Keywords: IP to Country Code,IP to Country
Author: Ronie Martinez
Author-email: ronmarti18@gmail.com
Requires-Python: >=3.6.1,<4
Classifier: Development Status :: 5 - Production/Stable
Classifier: License :: OSI Approved :: MIT License
Classifier: Programming Language :: Python :: 3
Classifier: Programming Language :: Python :: 3.6
Classifier: Programming Language :: Python :: 3.7
Classifier: Programming Language :: Python :: 3.8
Classifier: Programming Language :: Python :: Implementation :: CPython
Classifier: Topic :: Software Development :: Libraries :: Python Modules
Requires-Dist: pandas (>=1.0.1,<2.0.0)
Project-URL: Repository, https://github.com/roniemartinez/IPToCC
